unzippy.py
unzippy-0.1.0.dist-info/entry_points.txt
unzippy-0.1.0.dist-info/LICENSE
unzippy-0.1.0.dist-info/WHEEL
unzippy-0.1.0.dist-info/METADATA
unzippy-0.1.0.dist-info/RECORD
