Metadata-Version: 2.1
Name: unzippy
Version: 0.1.0
Summary: a command line application to `unzip` archives
Keywords: unzip,extract,archive
Author-email: Randy Schneck <i@rasch.co>
Classifier: License :: OSI Approved :: ISC License (ISCL)
Project-URL: Home, https://github.com/rasch/unzippy
